setup.py
Mirolyubov_lab3_new_version/CONSTANTS.py
Mirolyubov_lab3_new_version/__init__.py
Mirolyubov_lab3_new_version/factory.py
Mirolyubov_lab3_new_version/json_serializer.py
Mirolyubov_lab3_new_version/packing.py
Mirolyubov_lab3_new_version/xml_serializer.py
Mirolyubov_lab3_new_version.egg-info/PKG-INFO
Mirolyubov_lab3_new_version.egg-info/SOURCES.txt
Mirolyubov_lab3_new_version.egg-info/dependency_links.txt
Mirolyubov_lab3_new_version.egg-info/top_level.txt