Metadata-Version: 2.1
Name: Mirolyubov-lab3-new-version
Version: 3.0.1
Summary: Library for serialization JSON, XML
Author: Mirolyubov Ilya
Author-email: ilyamir1@mail.ru
